{
    "version": "0.1",
    "ignorePaths": [
        ".git",
        ".git/**",
        ".vscode/*",
        "node_modules",
        "**/node_modules",
        "**/node_modules/**",
        "node_modules/**"
    ],
    "language": "ru,en",
    "dictionaries": [],
    "words": [
        "Документооборот",
        "препроцессированным",
        "препроцессированных",
        "расширения",
        "рефакторинг",
        "Штрихкод",
        "Amadevus",
        "apos",
        "betke",
        "calcext",
        "Choco",
        "chocolately",
        "Codacy",
        "codecov",
        "codeql",
        "commitlint",
        "Committish",
        "compat",
        "concat",
        "datastyle",
        "dependabot",
        "dirstate",
        "documentfoundation",
        "dont",
        "drawooo",
        "editorconfig",
        "endregion",
        "environment",
        "formx",
        "gittools",
        "gitversion",
        "grddl",
        "ITGDSC",
        "ITGODT",
        "itgps",
        "libreoffice",
        "loext",
        "macrolib",
        "Markdig",
        "markdownlint",
        "mimetype",
        "mkdocs",
        "MSXML",
        "NMTOKEN",
        "Nuget",
        "officedocument",
        "officeooo",
        "oooc",
        "ooow",
        "ooxml",
        "opendocument",
        "openoffice",
        "Paren",
        "passwordprotected",
        "pobox",
        "precommit",
        "preprocess",
        "PreRelease",
        "pwsh",
        "qrcode",
        "readonly",
        "Recurse",
        "Remoting",
        "repo",
        "rsid",
        "sarif",
        "Segoe",
        "sergey",
        "shellcheck",
        "showvariable",
        "softprops",
        "streamable",
        "SXXP",
        "tableooo",
        "Tahoma",
        "toolbaritem",
        "unexisting",
        "VCARD",
        "vcards",
        "Veyor",
        "xcard",
        "xforms",
        "xlink"
    ],
    "ignoreRegExpList": [
        "эскалаци(я|и|ю|ей)",
        "автоответ(а|у|ом|е|ы|ов|ам|ами|ах)",
        "автоподстанов(ка|ки|ке|кой|ку|ки|ок|кам|ках)",
        "автозаполнени(е|я|ем|и|ю|й|ям|ях)",
        "AppVeyor",
        "репозитори(й|я|ю|ем|и)",
        "\\.gitattributes",
        "\\[.*?\\]\\(.*?\\)"
    ],
    "enableFiletypes": [
        "powershell",
        "xslt"
    ]
}